saddlebags/__init__.py
saddlebags/exceptions.py
saddlebags/saddlebag.py
saddlebags/test/__init__.py
saddlebags/test/test_saddlebag.py
saddlebags-1.3.1.dist-info/METADATA
saddlebags-1.3.1.dist-info/RECORD
saddlebags-1.3.1.dist-info/WHEEL
saddlebags-1.3.1.dist-info/top_level.txt
