Metadata-Version: 2.1
Name: saddlebags
Version: 1.3.1
Summary: Saddlebags provides easy loading and access to the data elements of JSON/YAML configuration files.
Home-page: https://github.com/eikonomega/saddlebags
Author: Michael Dunn
Author-email: mike@eikonomega.com
License: MIT
Keywords: configuration settings
Platform: UNKNOWN
Classifier: Intended Audience :: Developers
Classifier: Development Status :: 3 - Alpha
Classifier: Topic :: Software Development :: Libraries
Classifier: License :: OSI Approved :: MIT License
Classifier: Programming Language :: Python
Classifier: Programming Language :: Python :: 3.3
Classifier: Programming Language :: Python :: 3.4
Classifier: Programming Language :: Python :: 3.5
Classifier: Programming Language :: Python :: 3.6
Requires-Dist: pytest (<4,>=3)
Requires-Dist: PyYAML (<4,>=3.12)
